bittrade_luno/__init__.py
bittrade_luno/connection/__init__.py
bittrade_luno/connection/generic.py
bittrade_luno/connection/http.py
bittrade_luno/connection/private.py
bittrade_luno/connection/public.py
bittrade_luno/connection/reconnect.py
bittrade_luno/framework/__init__.py
bittrade_luno/framework/framework.py
bittrade_luno/models/__init__.py
bittrade_luno/models/endpoints.py
bittrade_luno/models/enhanced_websocket.py
bittrade_luno/models/framework.py
bittrade_luno/models/request_message.py
bittrade_luno/models/rest/cancel_order.py
bittrade_luno/models/rest/create_order.py
bittrade_luno/models/rest/list_trade.py
bittrade_luno/models/rest/order_book.py
bittrade_luno/rest/__init__.py
bittrade_luno/rest/cancel_order.py
bittrade_luno/rest/create_order.py
bittrade_luno/rest/http_factory_decorator.py
bittrade_luno/rest/list_trades.py
bittrade_luno/rest/top_orderbook.py
bittrade_luno-0.1.1.dist-info/WHEEL
bittrade_luno-0.1.1.dist-info/METADATA
bittrade_luno-0.1.1.dist-info/RECORD
