Metadata-Version: 2.1
Name: bittrade-luno
Version: 0.1.1
Summary: Reactive for luno
License: MIT
Author: Yu Jin
Author-email: adamlyj89@gmail.com
Requires-Python: >=3.11,<4.0
Classifier: License :: OSI Approved :: MIT License
Classifier: Programming Language :: Python :: 3
Classifier: Programming Language :: Python :: 3.11
Requires-Dist: asyncio (>=3.4.3,<4.0.0)
Requires-Dist: ccxt (==2.6.5)
Requires-Dist: elm-framework-helpers (>=0.3.1,<0.4.0)
Requires-Dist: expression (>=4.2.4,<5.0.0)
Requires-Dist: orjson (>=3.9.4,<4.0.0)
Requires-Dist: prompt-toolkit (>=3.0.39,<4.0.0)
Requires-Dist: ptpython (>=3.0.23,<4.0.0)
Requires-Dist: pydantic (==1.10.12)
Requires-Dist: reactivex (>=4.0.4,<5.0.0)
Requires-Dist: requests (>=2.31.0,<3.0.0)
Requires-Dist: rich (>=13.5.2,<14.0.0)
Requires-Dist: websocket-client (>=1.6.1,<2.0.0)
Requires-Dist: websockets (>=10.4,<11.0)
